examples/demo_boct_extraction.py
examples/demo_dicom_extraction.py
examples/demo_e2e_extraction.py
examples/demo_fda_extraction.py
examples/demo_fds_extraction.py
examples/demo_img_extraction.py
examples/demo_optovue_extraction.py
oct_converter/__init__.py
oct_converter/dicom/__init__.py
oct_converter/dicom/boct_meta.py
oct_converter/dicom/dicom.py
oct_converter/dicom/e2e_meta.py
oct_converter/dicom/fda_meta.py
oct_converter/dicom/fds_meta.py
oct_converter/dicom/img_meta.py
oct_converter/dicom/metadata.py
oct_converter/dicom/poct_meta.py
oct_converter/exceptions/__init__.py
oct_converter/image_types/__init__.py
oct_converter/image_types/fundus.py
oct_converter/image_types/oct.py
oct_converter/readers/__init__.py
oct_converter/readers/boct.py
oct_converter/readers/dicom.py
oct_converter/readers/e2e.py
oct_converter/readers/fda.py
oct_converter/readers/fds.py
oct_converter/readers/img.py
oct_converter/readers/poct.py
oct_converter/readers/read_dicom.py
oct_converter/readers/binary_structs/__init__.py
oct_converter/readers/binary_structs/boct_binary.py
oct_converter/readers/binary_structs/e2e_binary.py
oct_converter/readers/binary_structs/fda_binary.py
oct_converter/readers/binary_structs/fds_binary.py
oct_converter-0.6.2.dist-info/LICENSE
oct_converter-0.6.2.dist-info/METADATA
oct_converter-0.6.2.dist-info/WHEEL
oct_converter-0.6.2.dist-info/top_level.txt
oct_converter-0.6.2.dist-info/RECORD
