Metadata-Version: 2.1
Name: oct_converter
Version: 0.6.2
Summary: Extract OCT and fundus data from proprietary file formats.
Author-email: Mark Graham <markgraham539@gmail.com>
License: MIT License
Project-URL: Homepage, https://github.com/marksgraham/OCT-Converter
Keywords: oct,fundus,reader,fda,e2e,zeiss,heidelberg,topcon
Classifier: License :: OSI Approved :: MIT License
Classifier: Programming Language :: Python
Classifier: Programming Language :: Python :: 3
Requires-Python: >=3.7
License-File: LICENSE
Requires-Dist: construct
Requires-Dist: imageio
Requires-Dist: natsort
Requires-Dist: numpy
Requires-Dist: opencv-python
Requires-Dist: pydicom
Requires-Dist: matplotlib
Requires-Dist: imageio-ffmpeg
Requires-Dist: h5py
